snowconection/__init__.py
snowconection/utils.py
snowconection-0.1.dist-info/METADATA
snowconection-0.1.dist-info/WHEEL
snowconection-0.1.dist-info/top_level.txt
snowconection-0.1.dist-info/RECORD
