Metadata-Version: 2.1
Name: snowconection
Version: 0.1
Summary: A library with reusable functions
Home-page: 
Author: Tu Nombre
Author-email: carlitos8medina@gmail.com
License: MIT
Classifier: Programming Language :: Python :: 3
Classifier: License :: OSI Approved :: MIT License
Classifier: Operating System :: OS Independent
Requires-Python: >=3.6
